initify/__init__.py
initify-0.1.5.dist-info/DESCRIPTION.rst
initify-0.1.5.dist-info/METADATA
initify-0.1.5.dist-info/RECORD
initify-0.1.5.dist-info/WHEEL
initify-0.1.5.dist-info/metadata.json
initify-0.1.5.dist-info/top_level.txt
