Metadata-Version: 2.0
Name: initify
Version: 0.1.5
Summary: Simplify your __init__(self) function.
Home-page: https://github.com/prankymat/initify.py
Author: Matthew Wo
Author-email: 9029537@gmail.com
License: MIT
Platform: UNKNOWN
